pseudoprimes/__init__.py
pseudoprimes/baillie_psw.py
pseudoprimes/constants.py
pseudoprimes/lucas.py
pseudoprimes/miller_rabin.py
pseudoprimes/pseudoprimes.py
pseudoprimes/py.typed
pseudoprimes-2022.5.1.dist-info/LICENSE
pseudoprimes-2022.5.1.dist-info/METADATA
pseudoprimes-2022.5.1.dist-info/WHEEL
pseudoprimes-2022.5.1.dist-info/top_level.txt
pseudoprimes-2022.5.1.dist-info/RECORD
