Metadata-Version: 2.1
Name: pseudoprimes
Version: 2022.5.1
Summary: Test and find prime numbers
Home-page: https://github.com/oittaa/pseudoprimes-py
Author: Oittaa
Author-email: 
License: UNKNOWN
Keywords: prime,primes,pseudoprimes,primality
Platform: UNKNOWN
Classifier: Development Status :: 3 - Alpha
Classifier: Intended Audience :: Developers
Classifier: License :: OSI Approved :: MIT License
Classifier: Operating System :: OS Independent
Classifier: Programming Language :: Python
Classifier: Programming Language :: Python :: 3
Classifier: Programming Language :: Python :: 3.8
Classifier: Programming Language :: Python :: 3.9
Classifier: Programming Language :: Python :: 3.10
Requires-Python: >=3.8
License-File: LICENSE
